{".class": "MypyFile", "_fullname": "backup_diary", "is_partial_stub_package": false, "is_stub": false, "names": {".class": "SymbolTable", "BaseCommand": {".class": "SymbolTableNode", "kind": "Gdef", "node": {".class": "Var", "flags": ["is_suppressed_import", "is_ready"], "fullname": "backup_diary.BaseCommand", "name": "BaseCommand", "type": {".class": "AnyType", "missing_import_name": "backup_diary.BaseCommand", "source_any": null, "type_of_any": 3}}}, "Command": {".class": "SymbolTableNode", "kind": "Gdef", "node": {".class": "TypeInfo", "_promote": null, "abstract_attributes": [], "bases": ["builtins.object"], "declared_metaclass": null, "defn": {".class": "ClassDef", "fullname": "backup_diary.Command", "name": "Command", "type_vars": []}, "flags": ["fallback_to_any"], "fullname": "backup_diary.Command", "metaclass_type": null, "metadata": {}, "module_name": "backup_diary", "mro": ["backup_diary.Command", "builtins.object"], "names": {".class": "SymbolTable", "file_path": {".class": "SymbolTableNode", "kind": "Mdef", "node": {".class": "Var", "flags": ["is_initialized_in_class"], "fullname": "backup_diary.Command.file_path", "name": "file_path", "type": {".class": "AnyType", "missing_import_name": "backup_diary.settings", "source_any": {".class": "AnyType", "missing_import_name": "backup_diary.settings", "source_any": null, "type_of_any": 3}, "type_of_any": 7}}}, "handle": {".class": "SymbolTableNode", "kind": "Mdef", "node": {".class": "FuncDef", "arg_kinds": [0, 2, 4], "arg_names": ["self", "args", "options"], "flags": [], "fullname": "backup_diary.Command.handle", "name": "handle", "type": null}}, "help": {".class": "SymbolTableNode", "kind": "Mdef", "node": {".class": "Var", "flags": ["is_initialized_in_class", "is_ready"], "fullname": "backup_diary.Command.help", "name": "help", "type": "builtins.str"}}}, "tuple_type": null, "type_vars": [], "typeddict_type": null}}, "Diary": {".class": "SymbolTableNode", "kind": "Gdef", "node": {".class": "Var", "flags": ["is_suppressed_import", "is_ready"], "fullname": "backup_diary.Diary", "name": "Diary", "type": {".class": "AnyType", "missing_import_name": "backup_diary.Diary", "source_any": null, "type_of_any": 3}}}, "__doc__": {".class": "SymbolTableNode", "kind": "Gdef", "node": {".class": "Var", "flags": ["is_ready"], "fullname": "backup_diary.__doc__", "name": "__doc__", "type": "builtins.str"}}, "__file__": {".class": "SymbolTableNode", "kind": "Gdef", "node": {".class": "Var", "flags": ["is_ready"], "fullname": "backup_diary.__file__", "name": "__file__", "type": "builtins.str"}}, "__name__": {".class": "SymbolTableNode", "kind": "Gdef", "node": {".class": "Var", "flags": ["is_ready"], "fullname": "backup_diary.__name__", "name": "__name__", "type": "builtins.str"}}, "__package__": {".class": "SymbolTableNode", "kind": "Gdef", "node": {".class": "Var", "flags": ["is_ready"], "fullname": "backup_diary.__package__", "name": "__package__", "type": "builtins.str"}}, "csv": {".class": "SymbolTableNode", "cross_ref": "csv", "kind": "Gdef"}, "datetime": {".class": "SymbolTableNode", "cross_ref": "datetime", "kind": "Gdef"}, "os": {".class": "SymbolTableNode", "cross_ref": "os", "kind": "Gdef"}, "settings": {".class": "SymbolTableNode", "kind": "Gdef", "node": {".class": "Var", "flags": ["is_suppressed_import", "is_ready"], "fullname": "backup_diary.settings", "name": "settings", "type": {".class": "AnyType", "missing_import_name": "backup_diary.settings", "source_any": null, "type_of_any": 3}}}}, "path": "/Users/miyamotokoutarou/Desktop/new_portfolio/venv_private_diary/private_diary/diary/templates/backup_diary.py"}